model2api/__init__.py
model2api/_cli.py
model2api/core.py
model2api/api/__init__.py
model2api/api/fastapi_app.py
model2api/api/fastapi_utils.py
model2api/api/logging.py
tests/__init__.py
tests/test_core.py
tests/test_fastapi_app.py
model2api-0.0.3.dist-info/LICENSE
model2api-0.0.3.dist-info/METADATA
model2api-0.0.3.dist-info/WHEEL
model2api-0.0.3.dist-info/entry_points.txt
model2api-0.0.3.dist-info/top_level.txt
model2api-0.0.3.dist-info/RECORD
