Metadata-Version: 2.1
Name: model2api
Version: 0.0.3
Summary: Package to transform python functions into state of the art REST API
Home-page: https://github.com/dubuisa/model2api
Author: Antoine Dubuis
Author-email: antoine.dubuis@gmail.com
Project-URL: Homepage, https://github.com/dubuisa/model2api
Keywords: model deployer fastapi model2api api rest
Classifier: Programming Language :: Python :: 3.7
Classifier: Programming Language :: Python :: 3.8
Classifier: Programming Language :: Python :: 3.9
Classifier: Topic :: Utilities
Classifier: License :: OSI Approved :: MIT License
Requires-Python: >=3.7
License-File: LICENSE
Requires-Dist: fastapi
Requires-Dist: python-multipart
Requires-Dist: typer
Requires-Dist: asgi-correlation-id
Requires-Dist: loguru
Requires-Dist: uvicorn
